setup.py
textwrap.py
micropython_textwrap.egg-info/PKG-INFO
micropython_textwrap.egg-info/SOURCES.txt
micropython_textwrap.egg-info/dependency_links.txt
micropython_textwrap.egg-info/top_level.txt